bspmap/__init__.py
bspmap/basis.py
bspmap/bsp.py
bspmap/capi.py
bspmap/bin/bspmap.dll
bspmap/utils/timerecorder.py
bspmap-0.1.0.dist-info/METADATA
bspmap-0.1.0.dist-info/WHEEL
bspmap-0.1.0.dist-info/top_level.txt
bspmap-0.1.0.dist-info/RECORD
