Metadata-Version: 2.4
Name: bspmap
Version: 0.1.0
Summary: B-spline library with C++ backend
Author-email: Song Zenan <243919588@qq.com>
Requires-Python: >=3.12
Requires-Dist: numpy>=2.0.0
